file_groups/__init__.py
file_groups/compare_files.py
file_groups/config_files.py
file_groups/groups.py
file_groups/handler.py
file_groups/handler_compare.py
file_groups/py.typed
file_groups/types.py
file_groups-0.3.1.dist-info/LICENSE.txt
file_groups-0.3.1.dist-info/METADATA
file_groups-0.3.1.dist-info/WHEEL
file_groups-0.3.1.dist-info/top_level.txt
file_groups-0.3.1.dist-info/zip-safe
file_groups-0.3.1.dist-info/RECORD
