Metadata-Version: 2.1
Name: file_groups
Version: 0.3.1
Summary: Group files into 'protect' and 'work_on' and provide operations for safe delete/move and symlink handling.
Home-page: https://github.com/lhupfeldt/file_groups.git
Author: Lars Hupfeldt Nielsen
Author-email: lhn@hupfeldtit.dk
License: BSD
Classifier: Development Status :: 4 - Beta
Classifier: Intended Audience :: Developers
Classifier: License :: OSI Approved :: BSD License
Classifier: Natural Language :: English
Classifier: Operating System :: OS Independent
Classifier: Programming Language :: Python :: 3.13
Classifier: Programming Language :: Python :: 3.12
Classifier: Programming Language :: Python :: 3.11
Classifier: Programming Language :: Python :: 3.10
Classifier: Topic :: Software Development :: Libraries
Requires-Python: >=3.10
License-File: LICENSE.txt
Requires-Dist: appdirs>=1.4.4
Provides-Extra: dev
Requires-Dist: nox; extra == "dev"
